silero_api_server/__init__.py
silero_api_server/__main__.py
silero_api_server/server.py
silero_api_server/tts.py
silero_api_server-0.3.1.dist-info/METADATA
silero_api_server-0.3.1.dist-info/WHEEL
silero_api_server-0.3.1.dist-info/licenses/LICENSE
silero_api_server-0.3.1.dist-info/RECORD
