Metadata-Version: 2.1
Name: silero-api-server
Version: 0.3.1
Summary: A simple FastAPI server to host Silero TTS
Project-URL: Homepage, https://github.com/ouoertheo/silero-api-server
Project-URL: Bug Tracker, https://github.com/ouoertheo/silero-api-server/issues
Author-email: Ouoertheo <ouoertheo@tomeofjamin.net>
License-File: LICENSE
Classifier: License :: OSI Approved :: MIT License
Classifier: Operating System :: OS Independent
Classifier: Programming Language :: Python :: 3
Requires-Python: >=3.7
Requires-Dist: fastapi
Requires-Dist: loguru
Requires-Dist: numpy
Requires-Dist: pydantic
Requires-Dist: pydub
Requires-Dist: python-dotenv
Requires-Dist: soundfile
Requires-Dist: torch
Requires-Dist: torchaudio
Requires-Dist: uvicorn
